rp_poetry/__init__.py
rp_poetry-0.1.0.dist-info/METADATA
rp_poetry-0.1.0.dist-info/WHEEL
rp_poetry-0.1.0.dist-info/RECORD
